frhyme/__init__.py
frhyme/buildtrie.py
frhyme/compresstrie.py
frhyme/frhyme.json
frhyme/frhyme.py
frhyme-0.3.dist-info/LICENSE
frhyme-0.3.dist-info/METADATA
frhyme-0.3.dist-info/WHEEL
frhyme-0.3.dist-info/top_level.txt
frhyme-0.3.dist-info/RECORD
