Metadata-Version: 2.1
Name: frhyme
Version: 0.3
Summary: Guess the last phonemes of a French word
Home-page: https://gitlab.com/a3nm/frhyme
Author: Antoine Amarilli
Author-email: a3nm@a3nm.net
License: UNKNOWN
Platform: UNKNOWN
Classifier: Programming Language :: Python :: 3
